{
    "annotations": {
        "list": [
            {
                "builtIn": 1,
                "datasource": {
                    "type": "grafana",
                    "uid": "-- Grafana --"
                },
                "enable": true,
                "hide": true,
                "iconColor": "rgba(0, 211, 255, 1)",
                "name": "Annotations & Alerts",
                "type": "dashboard"
            }
        ]
    },
    "editable": true,
    "fiscalYearStartMonth": 0,
    "graphTooltip": 0,
    "id": 4,
    "links": [],
    "panels": [
        {
            "datasource": {
                "type": "prometheus",
                "uid": "PBFA97CFB590B2093"
            },
            "fieldConfig": {
                "defaults": {
                    "color": {
                        "mode": "thresholds"
                    },
                    "decimals": 1,
                    "mappings": [],
                    "max": 100,
                    "min": 0,
                    "thresholds": {
                        "mode": "absolute",
                        "steps": [
                            {
                                "color": "green",
                                "value": null
                            },
                            {
                                "color": "red",
                                "value": 80
                            }
                        ]
                    }
                },
                "overrides": []
            },
            "gridPos": {
                "h": 8,
                "w": 12,
                "x": 0,
                "y": 0
            },
            "id": 1,
            "options": {
                "minVizHeight": 75,
                "minVizWidth": 75,
                "orientation": "auto",
                "reduceOptions": {
                    "calcs": ["lastNotNull"],
                    "fields": "",
                    "values": false
                },
                "showThresholdLabels": false,
                "showThresholdMarkers": true,
                "sizing": "auto"
            },
            "pluginVersion": "11.5.2",
            "targets": [
                {
                    "datasource": {
                        "type": "prometheus",
                        "uid": "PBFA97CFB590B2093"
                    },
                    "disableTextWrap": false,
                    "editorMode": "code",
                    "expr": "100 * avg(irate(dotnet_process_cpu_time_seconds_total{exported_job=\"identity-api\"}[5m])) / (max(dotnet_process_cpu_count{exported_job=\"identity-api\"}) / 2)",
                    "fullMetaSearch": false,
                    "includeNullMetadata": true,
                    "legendFormat": "__auto",
                    "range": true,
                    "refId": "A",
                    "useBackend": false
                }
            ],
            "title": "Identity Gateway CPU Load",
            "type": "gauge"
        },
        {
            "datasource": {
                "type": "prometheus",
                "uid": "PBFA97CFB590B2093"
            },
            "fieldConfig": {
                "defaults": {
                    "color": {
                        "mode": "thresholds"
                    },
                    "decimals": 1,
                    "mappings": [],
                    "max": 100,
                    "min": 0,
                    "thresholds": {
                        "mode": "absolute",
                        "steps": [
                            {
                                "color": "green",
                                "value": null
                            },
                            {
                                "color": "red",
                                "value": 80
                            }
                        ]
                    }
                },
                "overrides": []
            },
            "gridPos": {
                "h": 8,
                "w": 12,
                "x": 12,
                "y": 0
            },
            "id": 3,
            "options": {
                "minVizHeight": 75,
                "minVizWidth": 75,
                "orientation": "auto",
                "reduceOptions": {
                    "calcs": ["lastNotNull"],
                    "fields": "",
                    "values": false
                },
                "showThresholdLabels": false,
                "showThresholdMarkers": true,
                "sizing": "auto"
            },
            "pluginVersion": "11.5.2",
            "targets": [
                {
                    "datasource": {
                        "type": "prometheus",
                        "uid": "PBFA97CFB590B2093"
                    },
                    "disableTextWrap": false,
                    "editorMode": "code",
                    "expr": "100 * avg(irate(dotnet_process_cpu_time_seconds_total{exported_job=\"webapp\"}[5m])) / (max(dotnet_process_cpu_count{exported_job=\"webapp\"}) / 2)",
                    "fullMetaSearch": false,
                    "includeNullMetadata": true,
                    "legendFormat": "__auto",
                    "range": true,
                    "refId": "A",
                    "useBackend": false
                }
            ],
            "title": "Web App CPU Load",
            "type": "gauge"
        },
        {
            "datasource": {
                "type": "prometheus",
                "uid": "PBFA97CFB590B2093"
            },
            "fieldConfig": {
                "defaults": {
                    "color": {
                        "mode": "palette-classic"
                    },
                    "custom": {
                        "axisBorderShow": false,
                        "axisCenteredZero": false,
                        "axisColorMode": "text",
                        "axisLabel": "",
                        "axisPlacement": "auto",
                        "barAlignment": 0,
                        "barWidthFactor": 0.6,
                        "drawStyle": "line",
                        "fillOpacity": 0,
                        "gradientMode": "none",
                        "hideFrom": {
                            "legend": false,
                            "tooltip": false,
                            "viz": false
                        },
                        "insertNulls": false,
                        "lineInterpolation": "linear",
                        "lineWidth": 1,
                        "pointSize": 5,
                        "scaleDistribution": {
                            "type": "linear"
                        },
                        "showPoints": "auto",
                        "spanNulls": false,
                        "stacking": {
                            "group": "A",
                            "mode": "none"
                        },
                        "thresholdsStyle": {
                            "mode": "off"
                        }
                    },
                    "mappings": [],
                    "thresholds": {
                        "mode": "absolute",
                        "steps": [
                            {
                                "color": "green",
                                "value": null
                            },
                            {
                                "color": "red",
                                "value": 80
                            }
                        ]
                    }
                },
                "overrides": []
            },
            "gridPos": {
                "h": 8,
                "w": 24,
                "x": 0,
                "y": 8
            },
            "id": 2,
            "options": {
                "legend": {
                    "calcs": [],
                    "displayMode": "list",
                    "placement": "bottom",
                    "showLegend": true
                },
                "tooltip": {
                    "hideZeros": false,
                    "mode": "single",
                    "sort": "none"
                }
            },
            "pluginVersion": "11.5.2",
            "targets": [
                {
                    "disableTextWrap": false,
                    "editorMode": "code",
                    "expr": "sum by(exported_job) (rate(http_client_open_connections[5m]))",
                    "fullMetaSearch": false,
                    "includeNullMetadata": true,
                    "legendFormat": "__auto",
                    "range": true,
                    "refId": "A",
                    "useBackend": false
                }
            ],
            "title": "Concurrent Users",
            "type": "timeseries"
        }
    ],
    "preload": false,
    "refresh": "5s",
    "schemaVersion": 40,
    "tags": [],
    "templating": {
        "list": []
    },
    "time": {
        "from": "now-5m",
        "to": "now"
    },
    "timepicker": {},
    "timezone": "browser",
    "title": "Load Monitoring",
    "uid": "beffauruzl9tsa",
    "version": 2,
    "weekStart": ""
}
